[
    {
        "content": "<p>Fwiw, I found an <a href=\"https://github.com/shashi/FileTrees.jl/issues/60\">issue</a>  with the parallelism in my program where 95% of work ended up on a single worker. After fixing it I seem to be able to scale things up as much as I want to. Perhaps the worker was so overworked it could not respond?</p>",
        "id": 258697726,
        "sender_full_name": "DrChainsaw",
        "timestamp": 1634901787
    },
    {
        "content": "<p><span class=\"user-mention silent\" data-user-id=\"300483\">DrChainsaw</span> has marked this topic as resolved.</p>",
        "id": 258697821,
        "sender_full_name": "Notification Bot",
        "timestamp": 1634901845
    },
    {
        "content": "<p>I was reading <a href=\"http://slendermeans.org/julia-iterators.html\">this </a> blog trying to understand how iterators work </p>\n<p>I tried to adapt the following script using the iterate function in place of start (), next () and done () . With some difficulty, but in the end I succeeded. </p>\n<p>#######<br>\n Jeff Bezanson • 8 years ago</p>\n<p>Very nice and thorough discussion of julia iterators!</p>\n<p>I'm surprised the fibonacci example uses mutation, since it is very naturally functional:</p>\n<div class=\"codehilite\" data-code-language=\"Julia\"><pre><span></span><code><span class=\"n\">immutable</span> <span class=\"n\">Fibs</span>\n<span class=\"k\">end</span>\n\n<span class=\"n\">start</span><span class=\"p\">(</span><span class=\"n\">f</span><span class=\"o\">::</span><span class=\"kt\">Fibs</span><span class=\"p\">)</span> <span class=\"o\">=</span> <span class=\"p\">(</span><span class=\"mi\">0</span><span class=\"p\">,</span> <span class=\"mi\">1</span><span class=\"p\">)</span>\n<span class=\"n\">next</span><span class=\"p\">(</span><span class=\"n\">f</span><span class=\"o\">::</span><span class=\"kt\">Fibs</span><span class=\"p\">,</span> <span class=\"n\">st</span><span class=\"p\">)</span> <span class=\"o\">=</span> <span class=\"p\">(</span><span class=\"n\">st</span><span class=\"p\">[</span><span class=\"mi\">2</span><span class=\"p\">],</span> <span class=\"p\">(</span><span class=\"n\">st</span><span class=\"p\">[</span><span class=\"mi\">2</span><span class=\"p\">],</span> <span class=\"n\">st</span><span class=\"p\">[</span><span class=\"mi\">1</span><span class=\"p\">]</span><span class=\"o\">+</span><span class=\"n\">st</span><span class=\"p\">[</span><span class=\"mi\">2</span><span class=\"p\">]))</span>\n<span class=\"n\">done</span><span class=\"p\">(</span><span class=\"n\">f</span><span class=\"o\">::</span><span class=\"kt\">Fibs</span><span class=\"p\">,</span> <span class=\"n\">st</span><span class=\"p\">)</span> <span class=\"o\">=</span> <span class=\"nb\">false</span>\n</code></pre></div>\n<p>Then you can do e.g. <code>take(Fibs(), 10)</code> (using the Iterators package).</p>\n<p>#################</p>\n<div class=\"codehilite\" data-code-language=\"Julia\"><pre><span></span><code><span class=\"k\">struct</span> <span class=\"kt\">Fibs</span>\n<span class=\"k\">end</span>\n\n<span class=\"n\">Base</span><span class=\"o\">.</span><span class=\"n\">iterate</span><span class=\"p\">(</span><span class=\"n\">f</span><span class=\"o\">::</span><span class=\"kt\">Fibs</span><span class=\"p\">)</span> <span class=\"o\">=</span> <span class=\"p\">(</span><span class=\"mi\">0</span><span class=\"p\">,(</span><span class=\"mi\">0</span><span class=\"p\">,</span> <span class=\"mi\">1</span><span class=\"p\">))</span>\n<span class=\"n\">Base</span><span class=\"o\">.</span><span class=\"n\">iterate</span><span class=\"p\">(</span><span class=\"n\">f</span><span class=\"o\">::</span><span class=\"kt\">Fibs</span><span class=\"p\">,</span> <span class=\"n\">st</span><span class=\"p\">)</span> <span class=\"o\">=</span> <span class=\"p\">(</span><span class=\"n\">st</span><span class=\"p\">[</span><span class=\"mi\">2</span><span class=\"p\">],</span> <span class=\"p\">(</span><span class=\"n\">st</span><span class=\"p\">[</span><span class=\"mi\">2</span><span class=\"p\">],</span> <span class=\"n\">st</span><span class=\"p\">[</span><span class=\"mi\">1</span><span class=\"p\">]</span><span class=\"o\">+</span><span class=\"n\">st</span><span class=\"p\">[</span><span class=\"mi\">2</span><span class=\"p\">]))</span>\n\n<span class=\"k\">using</span> <span class=\"n\">IterTools</span>\n\n<span class=\"n\">collect</span><span class=\"p\">(</span><span class=\"n\">takestrict</span><span class=\"p\">(</span><span class=\"n\">Fibs</span><span class=\"p\">(),</span><span class=\"mi\">10</span><span class=\"p\">))</span>\n</code></pre></div>\n<p>I tried later to define a non-infinite iterator, as follows: </p>\n<div class=\"codehilite\" data-code-language=\"Julia\"><pre><span></span><code><span class=\"k\">struct</span> <span class=\"kt\">Fibn</span>\n    <span class=\"n\">n</span><span class=\"o\">::</span><span class=\"kt\">Int</span>\n<span class=\"k\">end</span>\n\n<span class=\"n\">ϕ</span><span class=\"o\">=</span><span class=\"mi\">2</span><span class=\"o\">/</span><span class=\"p\">(</span><span class=\"mi\">1</span><span class=\"o\">-</span><span class=\"n\">sqrt</span><span class=\"p\">(</span><span class=\"mi\">5</span><span class=\"p\">))</span>\n<span class=\"n\">fb</span><span class=\"p\">(</span><span class=\"n\">n</span><span class=\"p\">)</span><span class=\"o\">=</span><span class=\"kt\">Int</span><span class=\"p\">(</span><span class=\"n\">trunc</span><span class=\"p\">((</span><span class=\"n\">ϕ</span><span class=\"o\">^</span><span class=\"n\">n</span> <span class=\"o\">-</span><span class=\"p\">(</span><span class=\"o\">-</span><span class=\"n\">ϕ</span><span class=\"p\">)</span><span class=\"o\">^</span><span class=\"p\">(</span><span class=\"o\">-</span><span class=\"n\">n</span><span class=\"p\">))</span><span class=\"o\">/</span><span class=\"n\">sqrt</span><span class=\"p\">(</span><span class=\"mi\">5</span><span class=\"p\">)</span><span class=\"o\">*</span><span class=\"p\">(</span><span class=\"o\">-</span><span class=\"mi\">1</span><span class=\"p\">)</span><span class=\"o\">^</span><span class=\"n\">n</span><span class=\"p\">))</span>\n\n<span class=\"n\">f</span><span class=\"p\">(</span><span class=\"n\">n</span><span class=\"p\">)</span><span class=\"o\">=</span><span class=\"n\">Fibn</span><span class=\"p\">(</span><span class=\"n\">n</span><span class=\"p\">)</span>\n<span class=\"n\">length</span><span class=\"p\">(</span><span class=\"n\">f</span><span class=\"o\">::</span><span class=\"kt\">Fibn</span><span class=\"p\">)</span><span class=\"o\">=</span><span class=\"n\">f</span><span class=\"o\">.</span><span class=\"n\">n</span>\n<span class=\"n\">Base</span><span class=\"o\">.</span><span class=\"n\">iterate</span><span class=\"p\">(</span><span class=\"n\">f</span><span class=\"o\">::</span><span class=\"kt\">Fibn</span><span class=\"p\">)</span> <span class=\"o\">=</span> <span class=\"p\">(</span><span class=\"mi\">0</span><span class=\"p\">,(</span><span class=\"mi\">0</span><span class=\"p\">,</span> <span class=\"mi\">1</span><span class=\"p\">))</span>\n<span class=\"n\">Base</span><span class=\"o\">.</span><span class=\"n\">iterate</span><span class=\"p\">(</span><span class=\"n\">f</span><span class=\"o\">::</span><span class=\"kt\">Fibn</span><span class=\"p\">,</span> <span class=\"n\">st</span><span class=\"p\">)</span> <span class=\"o\">=</span> <span class=\"n\">st</span><span class=\"p\">[</span><span class=\"mi\">1</span><span class=\"p\">]</span> <span class=\"o\">&lt;=</span> <span class=\"n\">fb</span><span class=\"p\">(</span><span class=\"n\">f</span><span class=\"o\">.</span><span class=\"n\">n</span><span class=\"o\">-</span><span class=\"mi\">1</span><span class=\"p\">)</span> <span class=\"o\">?</span> <span class=\"p\">(</span><span class=\"n\">st</span><span class=\"p\">[</span><span class=\"mi\">2</span><span class=\"p\">],</span> <span class=\"p\">(</span><span class=\"n\">st</span><span class=\"p\">[</span><span class=\"mi\">2</span><span class=\"p\">],</span> <span class=\"n\">st</span><span class=\"p\">[</span><span class=\"mi\">1</span><span class=\"p\">]</span><span class=\"o\">+</span><span class=\"n\">st</span><span class=\"p\">[</span><span class=\"mi\">2</span><span class=\"p\">]))</span> <span class=\"o\">:</span> <span class=\"nb\">nothing</span>\n\n<span class=\"k\">using</span> <span class=\"n\">IterTools</span>\n\n<span class=\"k\">for</span> <span class=\"n\">i</span><span class=\"o\">=</span><span class=\"n\">f</span><span class=\"p\">(</span><span class=\"mi\">10</span><span class=\"p\">)</span>\n    <span class=\"n\">println</span><span class=\"p\">(</span><span class=\"n\">i</span><span class=\"p\">)</span>\n<span class=\"k\">end</span>\n</code></pre></div>\n<p>I just wanted to do an exercise on iterators, it's not meant to be a solution to some real problem. <br>\nI was unable to fix things to get the collect () function to work though.</p>\n<div class=\"codehilite\" data-code-language=\"Julia\"><pre><span></span><code><span class=\"n\">julia</span><span class=\"o\">&gt;</span> <span class=\"n\">collect</span><span class=\"p\">(</span><span class=\"n\">f</span><span class=\"p\">(</span><span class=\"mi\">10</span><span class=\"p\">))</span>\n<span class=\"n\">ERROR</span><span class=\"o\">:</span> <span class=\"kt\">MethodError</span><span class=\"o\">:</span> <span class=\"n\">no</span> <span class=\"n\">method</span> <span class=\"n\">matching</span> <span class=\"n\">length</span><span class=\"p\">(</span><span class=\"o\">::</span><span class=\"kt\">Fibn</span><span class=\"p\">)</span>\n</code></pre></div>\n<p>How should I do instead of ...? </p>\n<div class=\"codehilite\" data-code-language=\"Julia\"><pre><span></span><code><span class=\"n\">length</span><span class=\"p\">(</span><span class=\"n\">f</span><span class=\"o\">::</span><span class=\"kt\">Fibn</span><span class=\"p\">)</span><span class=\"o\">=</span><span class=\"n\">f</span><span class=\"o\">.</span><span class=\"n\">n</span>\n</code></pre></div>",
        "id": 258832192,
        "sender_full_name": "rocco sprmnt21",
        "timestamp": 1635007595
    }
]